tests
tornado_angular
