Metadata-Version: 1.1
Name: tornado-angular
Version: 0.2.1
Summary: tornado-angular is an opinionated way of distributing angular applications with tornado web server as api handler.
Home-page: https://github.com/heynemann/tornado-angular
Author: Bernardo Heynemann
Author-email: heynemann@gmail.com
License: MIT
Keywords: tornado web angular api
Platform: UNKNOWN
Classifier: Development Status :: 4 - Beta
Classifier: Intended Audience :: Developers
Classifier: License :: OSI Approved :: MIT License
Classifier: Natural Language :: English
Classifier: Operating System :: Unix
Classifier: Programming Language :: Python :: 2.7
Classifier: Programming Language :: Python :: 3.4
Classifier: Programming Language :: Python :: Implementation :: PyPy
Classifier: Operating System :: OS Independent
